{
    "id": "0dut3WvOcYaEYEEPkBjp2D",
    "tracks": [
        {
            "track_id": "3nsfB1vus2qaloUdcBZvDu",
            "track_name": "All Too Well (Taylor's Version)",
            "track_artist": "Taylor Swift",
            "track_album": "Red (Taylor's Version)",
            "track_duration": 329160,
            "track_added_by": "marifer_salas",
            "track_added_at": "2021-11-12T20:20:27Z",
            "uri": "spotify:track:3nsfB1vus2qaloUdcBZvDu"
        },
        {
            "track_id": "4pfrrhvplbJZAIsfosGWQP",
            "track_name": "the 1",
            "track_artist": "Taylor Swift",
            "track_album": "folklore (deluxe version)",
            "track_duration": 210240,
            "track_added_by": "marifer_salas",
            "track_added_at": "2021-03-21T08:59:14Z",
            "uri": "spotify:track:4pfrrhvplbJZAIsfosGWQP"
        },
        {
            "track_id": "1gcyHQpBQ1lfXGdhZmWrHP",
            "track_name": "champagne problems",
            "track_artist": "Taylor Swift",
            "track_album": "evermore (deluxe version)",
            "track_duration": 244000,
            "track_added_by": "marifer_salas",
            "track_added_at": "2021-03-21T08:59:48Z",
            "uri": "spotify:track:1gcyHQpBQ1lfXGdhZmWrHP"
        },
        {
            "track_id": "0KRYCBwIpWYFNrXOmXbyUh",
            "track_name": "cardigan",
            "track_artist": "Taylor Swift",
            "track_album": "folklore (deluxe version)",
            "track_duration": 239560,
            "track_added_by": "marifer_salas",
            "track_added_at": "2021-03-21T08:59:21Z",
            "uri": "spotify:track:0KRYCBwIpWYFNrXOmXbyUh"
        },
        {
            "track_id": "6nK2pIKFcRc5frrZKHgsiT",
            "track_name": "august",
            "track_artist": "Taylor Swift",
            "track_album": "folklore (deluxe version)",
            "track_duration": 261920,
            "track_added_by": "marifer_salas",
            "track_added_at": "2021-03-21T08:59:28Z",
            "uri": "spotify:track:6nK2pIKFcRc5frrZKHgsiT"
        },
        {
            "track_id": "6sQckd3Z8NPxVVKUnavY1F",
            "track_name": "\u2018tis the damn season",
            "track_artist": "Taylor Swift",
            "track_album": "evermore (deluxe version)",
            "track_duration": 229840,
            "track_added_by": "marifer_salas",
            "track_added_at": "2021-03-21T08:59:52Z",
            "uri": "spotify:track:6sQckd3Z8NPxVVKUnavY1F"
        },
        {
            "track_id": "7cm50Lw03k6VvRauJtkyTj",
            "track_name": "this is me trying",
            "track_artist": "Taylor Swift",
            "track_album": "folklore (deluxe version)",
            "track_duration": 195106,
            "track_added_by": "marifer_salas",
            "track_added_at": "2021-03-21T08:59:33Z",
            "uri": "spotify:track:7cm50Lw03k6VvRauJtkyTj"
        },
        {
            "track_id": "2ehRU518I0hYqMGQnk4lDY",
            "track_name": "invisible string",
            "track_artist": "Taylor Swift",
            "track_album": "folklore (deluxe version)",
            "track_duration": 252880,
            "track_added_by": "marifer_salas",
            "track_added_at": "2021-03-21T08:59:38Z",
            "uri": "spotify:track:2ehRU518I0hYqMGQnk4lDY"
        },
        {
            "track_id": "7l2tmgUhV7Y2aJHjiszifg",
            "track_name": "Mr. Perfectly Fine (Taylor\u2019s Version) (From The Vault)",
            "track_artist": "Taylor Swift",
            "track_album": "Mr. Perfectly Fine (Taylor\u2019s Version) (From The Vault)",
            "track_duration": 277591,
            "track_added_by": "marifer_salas",
            "track_added_at": "2021-04-07T18:19:23Z",
            "uri": "spotify:track:7l2tmgUhV7Y2aJHjiszifg"
        },
        {
            "track_id": "22bPsP2jCgbLUvh82U0Z3M",
            "track_name": "The Way I Loved You (Taylor\u2019s Version)",
            "track_artist": "Taylor Swift",
            "track_album": "Fearless (Taylor's Version)",
            "track_duration": 243136,
            "track_added_by": "marifer_salas",
            "track_added_at": "2021-04-12T08:03:38Z",
            "uri": "spotify:track:22bPsP2jCgbLUvh82U0Z3M"
        },
        {
            "track_id": "1GwMQaZz6Au3QLDbjbMdme",
            "track_name": "Call It What You Want",
            "track_artist": "Taylor Swift",
            "track_album": "reputation",
            "track_duration": 203506,
            "track_added_by": "marifer_salas",
            "track_added_at": "2021-08-08T15:32:54Z",
            "uri": "spotify:track:1GwMQaZz6Au3QLDbjbMdme"
        },
        {
            "track_id": "2dgFqt3w9xIQRjhPtwNk3D",
            "track_name": "Death By A Thousand Cuts",
            "track_artist": "Taylor Swift",
            "track_album": "Lover",
            "track_duration": 198533,
            "track_added_by": "marifer_salas",
            "track_added_at": "2021-09-02T19:35:29Z",
            "uri": "spotify:track:2dgFqt3w9xIQRjhPtwNk3D"
        },
        {
            "track_id": "1Ov37jtRQ2YNAe8HzfczkL",
            "track_name": "Wildest Dreams (Taylor's Version)",
            "track_artist": "Taylor Swift",
            "track_album": "Wildest Dreams (Taylor's Version)",
            "track_duration": 220433,
            "track_added_by": "marifer_salas",
            "track_added_at": "2021-09-17T14:15:54Z",
            "uri": "spotify:track:1Ov37jtRQ2YNAe8HzfczkL"
        },
        {
            "track_id": "5enxwA8aAbwZbf5qCHORXi",
            "track_name": "All Too Well (10 Minute Version) (Taylor's Version) (From The Vault)",
            "track_artist": "Taylor Swift",
            "track_album": "Red (Taylor's Version)",
            "track_duration": 613026,
            "track_added_by": "marifer_salas",
            "track_added_at": "2021-11-17T04:49:28Z",
            "uri": "spotify:track:5enxwA8aAbwZbf5qCHORXi"
        }
    ]
}